fontFeatures/__init__.py
fontFeatures/utils.py
fontFeatures/feaLib/Attachment.py
fontFeatures/feaLib/Chaining.py
fontFeatures/feaLib/FontFeatures.py
fontFeatures/feaLib/Positioning.py
fontFeatures/feaLib/Routine.py
fontFeatures/feaLib/RoutineReference.py
fontFeatures/feaLib/Substitution.py
fontFeatures/feaLib/__init__.py
fontFeatures/fontDameLib/__init__.py
fontFeatures/optimizer/FontFeatures.py
fontFeatures/optimizer/Routine.py
fontFeatures/optimizer/__init__.py
fontFeatures/shaperLib/ArabicShaper.py
fontFeatures/shaperLib/Attachment.py
fontFeatures/shaperLib/BaseShaper.py
fontFeatures/shaperLib/Buffer.py
fontFeatures/shaperLib/Chaining.py
fontFeatures/shaperLib/HangulShaper.py
fontFeatures/shaperLib/IndicShaper.py
fontFeatures/shaperLib/IndicShaperData.py
fontFeatures/shaperLib/KhmerShaper.py
fontFeatures/shaperLib/MyanmarShaper.py
fontFeatures/shaperLib/Positioning.py
fontFeatures/shaperLib/Routine.py
fontFeatures/shaperLib/Rule.py
fontFeatures/shaperLib/Shaper.py
fontFeatures/shaperLib/Substitution.py
fontFeatures/shaperLib/SyllabicShaper.py
fontFeatures/shaperLib/USEShaper.py
fontFeatures/shaperLib/VowelConstraints.py
fontFeatures/shaperLib/__init__.py
fontFeatures/ttLib/Attachment.py
fontFeatures/ttLib/Chaining.py
fontFeatures/ttLib/FontFeatures.py
fontFeatures/ttLib/GDEFUnparser.py
fontFeatures/ttLib/GPOSUnparser.py
fontFeatures/ttLib/GSUBUnparser.py
fontFeatures/ttLib/GTableUnparser.py
fontFeatures/ttLib/Positioning.py
fontFeatures/ttLib/Routine.py
fontFeatures/ttLib/Substitution.py
fontFeatures/ttLib/ValueRecord.py
fontFeatures/ttLib/__init__.py
fontFeatures/voltLib/__init__.py
fontFeatures/xmlLib/Attachment.py
fontFeatures/xmlLib/Chaining.py
fontFeatures/xmlLib/FontFeatures.py
fontFeatures/xmlLib/Positioning.py
fontFeatures/xmlLib/Routine.py
fontFeatures/xmlLib/RoutineReference.py
fontFeatures/xmlLib/Rule.py
fontFeatures/xmlLib/Substitution.py
fontFeatures/xmlLib/__init__.py
fontFeatures/xmlLib/utils.py
fontFeatures-1.8.0.data/scripts/ff-shape
fontFeatures-1.8.0.dist-info/LICENSE
fontFeatures-1.8.0.dist-info/METADATA
fontFeatures-1.8.0.dist-info/WHEEL
fontFeatures-1.8.0.dist-info/top_level.txt
fontFeatures-1.8.0.dist-info/RECORD
