Metadata-Version: 2.1
Name: fontFeatures
Version: 1.8.0
Summary: Python library for manipulating OpenType font features
Home-page: https://github.com/simoncozens/fontFeatures
Author: Simon Cozens
Author-email: simon@simon-cozens.org
License: MIT
Classifier: Programming Language :: Python
Classifier: Programming Language :: Python :: 2
Classifier: Programming Language :: Python :: 3
Classifier: License :: OSI Approved :: MIT License
Classifier: Development Status :: 4 - Beta
Provides-Extra: shaper
License-File: LICENSE
